Metadata-Version: 2.1
Name: NewBingImageCreator
Version: 2.2.4
Summary: .com
Home-page: https://github.com/
Author: Anonymous
Author-email: 
Requires-Dist: httpx
